config/__init__.py
configbetter/__init__.py
tests/__init__.py
tests/test___init__.py
config_better-1.1.0.dist-info/LICENSE
config_better-1.1.0.dist-info/METADATA
config_better-1.1.0.dist-info/WHEEL
config_better-1.1.0.dist-info/top_level.txt
config_better-1.1.0.dist-info/RECORD
